{
  "title": "email",
  "icon": "mail",
  "items": [
    {
      "name": "Betterbird",
      "link": "https://www.betterbird.eu/",
      "description": {
        "da": "Desktop e-mailklient",
        "en": "Desktop email client",
        "et": "Töölauameiliklient",
        "pl": "Klient poczty na komputer",
        "ru": "Десктопный почтовый клиент",
        "tok": "ilo e-mail pi ilo suli",
        "vi-Hani": "應用伊𩄲𨑗𣛠併",
        "vi": "Ứng dụng email trên máy tính",
        "zh": "桌面邮件应用"
      }
    },
    {
      "name": "Spark",
      "link": "https://sparkmailapp.com/",
      "description": {
        "da": "E-mailklient (desktop & mobil)",
        "en": "Email client (desktop & mobile)",
        "et": "E-posti klient (töölaud ja mobiil)",
        "pl": "Klient poczty (PC i mobilny)",
        "ru": "Почтовый клиент (десктоп и мобильный)",
        "tok": "ilo e-mail (ilo & ilo tawa)",
        "vi-Hani": "應用伊𩄲𨑗𣛠併吧電話",
        "vi": "Ứng dụng email trên máy tính & điện thoại",
        "zh": "桌面 & 移动邮件应用"
      }
    },
    {
      "name": "Zoho",
      "link": "https://www.zoho.com/mail/",
      "description": {
        "da": "Domain e-mailudbyder",
        "en": "Domain email provider",
        "et": "Domeeni e-posti teenusepakkuja",
        "pl": "Dostawca poczty dla domeny",
        "ru": "Провайдер почты для домена",
        "tok": "pana e e-mail pi nimi ma",
        "vi-Hani": "供給伊𩄲朱𠸜沔",
        "vi": "Cung cấp email cho tên miền",
        "zh": "域名邮箱提供商"
      }
    },
    {
      "name": "Proton Mail",
      "link": "https://proton.me/mail",
      "description": {
        "da": "Sikker e-mailudbyder",
        "en": "Secure email provider",
        "et": "Turvaline e-posti teenusepakkuja",
        "pl": "Bezpieczny dostawca poczty",
        "ru": "Безопасный провайдер электронной почты",
        "tok": "pana e e-mail awen",
        "vi-Hani": "供給伊𩄲保密",
        "vi": "Nhà cung cấp email bảo mật",
        "zh": "安全电子邮件提供商"
      }
    },
    {
      "name": "Tuta",
      "link": "https://tuta.com/",
      "description": {
        "da": "Sikker e-mailudbyder",
        "en": "Secure email provider",
        "et": "Turvaline e-posti teenusepakkuja",
        "pl": "Bezpieczny dostawca poczty",
        "ru": "Безопасный провайдер электронной почты",
        "tok": "pana e e-mail awen",
        "vi-Hani": "供給伊𩄲保密",
        "vi": "Nhà cung cấp email bảo mật",
        "zh": "安全电子邮件提供商"
      }
    },
    {
      "name": "Google Calendar",
      "description": {
        "da": "Kalender og planlægning",
        "en": "Calendar and scheduling",
        "et": "Kalender ja ajakava",
        "pl": "Kalendarz i planowanie",
        "ru": "Календарь и планирование",
        "tok": "tenpo & sitelen tenpo",
        "vi-Hani": "Lịch và lập kế hoạch",
        "vi": "Lịch và lập kế hoạch",
        "zh": "日历和计划"
      }
    },
    {
      "name": "KDE Connect",
      "link": "https://kdeconnect.kde.org/",
      "description": {
        "da": "Forbindelse mellem telefon og PC",
        "en": "Linking phone with PC",
        "et": "Telefoni ühendamine arvutiga",
        "pl": "Łączenie telefonu z komputerem",
        "ru": "Связь телефона с ПК",
        "tok": "linja ilo tawa & ilo suli",
        "vi-Hani": "結綏電話貝𣛠併",
        "vi": "Kết nối điện thoại với máy tính",
        "zh": "连接手机和电脑"
      }
    },
    {
      "name": "Notesnook",
      "link": "https://notesnook.com/",
      "description": {
        "da": "Note-app",
        "en": "Note-taking app",
        "et": "Märkmete rakendus",
        "pl": "Aplikacja do notatek",
        "ru": "Приложение для заметок",
        "tok": "ilo sitelen lili",
        "vi-Hani": "應用𥱬註",
        "vi": "Ứng dụng ghi chú",
        "zh": "笔记应用"
      }
    },
    {
      "name": "LibreOffice",
      "link": "https://www.libreoffice.org/",
      "description": {
        "da": "Office-pakke",
        "en": "Office suite",
        "et": "Kontoritarkvara",
        "pl": "Pakiet biurowy",
        "ru": "Офисный пакет",
        "tok": "ilo pali lipu",
        "vi-Hani": "Bộ ứng dụng văn phòng",
        "vi": "Bộ ứng dụng văn phòng",
        "zh": "办公套件"
      }
    }
  ]
}
