{
  "title": "video",
  "icon": "video",
  "items": [
    {
      "name": "DaVinci Resolve",
      "link": "https://www.blackmagicdesign.com/products/davinciresolve/",
      "description": {
        "da": "Professionel videoredigeringsprogram",
        "en": "Professional video editor",
        "et": "Professionaalne videoredaktor",
        "pl": "Profesjonalny edytor wideo",
        "ru": "Профессиональный видеоредактор",
        "tok": "ilo ante sitelen tawa pi jan suli",
        "vi-Hani": "Trình sửa video chuyên nghiệp",
        "vi": "Trình sửa video chuyên nghiệp",
        "zh": "专业视频编辑器"
      }
    },
    {
      "name": "Kdenlive",
      "link": "https://kdenlive.org/",
      "description": {
        "da": "Open source-videoredigeringsprogram",
        "en": "Open-source video editor",
        "et": "Avatud lähtekoodiga videoredaktor",
        "pl": "Edytor wideo open source",
        "ru": "Видеоредактор с открытым исходным кодом",
        "tok": "ilo ante sitelen tawa open source",
        "vi-Hani": "Trình sửa video mã nguồn mở",
        "vi": "Trình sửa video mã nguồn mở",
        "zh": "开源视频编辑器"
      }
    },
    {
      "name": "CapCut",
      "link": "https://www.capcut.com/",
      "description": {
        "da": "Videoredigeringsprogram (desktop & mobil)",
        "en": "Video editor (desktop & mobile)",
        "et": "Videoredaktor (töölaud ja mobiil)",
        "pl": "Edytor wideo (PC i mobilny)",
        "ru": "Видеоредактор (десктоп и мобильный)",
        "tok": "ilo ante sitelen tawa (ilo & ilo tawa)",
        "vi-Hani": "Trình sửa video",
        "vi": "Trình sửa video",
        "zh": "视频编辑器"
      }
    },
    {
      "name": "Aegisub",
      "link": "http://www.aegisub.org/",
      "description": {
        "da": "Underteksteditor",
        "en": "Subtitle editor",
        "et": "Subtiitrite redaktor",
        "pl": "Edytor napisów",
        "ru": "Редактор субтитров",
        "tok": "ilo sitelen anpa kalama",
        "vi-Hani": "Trình tạo phụ đề",
        "vi": "Trình tạo phụ đề",
        "zh": "字幕编辑器"
      }
    },
    {
      "name": "Cine",
      "link": "https://github.com/diegopvlk/Cine",
      "description": {
        "da": "Videoafspiller",
        "en": "Video player",
        "et": "Videopleier",
        "pl": "Odtwarzacz wideo",
        "ru": "Видеоплеер",
        "tok": "ilo lukin sitelen tawa",
        "vi-Hani": "Trình phát video",
        "vi": "Trình phát video",
        "zh": "视频播放器"
      }
    },
    {
      "name": "Audacity",
      "link": "https://www.audacityteam.org/",
      "description": {
        "da": "Lydredigeringsprogram",
        "en": "Audio editor",
        "et": "Heliredaktor",
        "pl": "Edytor audio",
        "ru": "Аудиоредактор",
        "tok": "ilo ante kalama",
        "vi-Hani": "Trình sửa âm thanh",
        "vi": "Trình sửa âm thanh",
        "zh": "音频编辑器"
      }
    },
    {
      "name": "GIMP",
      "link": "https://www.gimp.org/",
      "description": {
        "da": "Open source-fotoredigeringsprogram",
        "en": "Open-source photo editor",
        "et": "Avatud lähtekoodiga fototöötleja",
        "pl": "Edytor zdjęć open source",
        "ru": "Фоторедактор с открытым исходным кодом",
        "tok": "ilo ante sitelen open source",
        "vi-Hani": "Trình sửa ảnh mã nguồn mở",
        "vi": "Trình sửa ảnh mã nguồn mở",
        "zh": "开源照片编辑器"
      }
    }
  ]
}
